flux/__init__.py
flux/app.py
flux/cli.py
flux/config.py
flux/debouncer.py
flux/runner.py
flux/watcher.py
flux_reload-0.1.0.dist-info/METADATA
flux_reload-0.1.0.dist-info/WHEEL
flux_reload-0.1.0.dist-info/entry_points.txt
flux_reload-0.1.0.dist-info/top_level.txt
flux_reload-0.1.0.dist-info/RECORD
