Metadata-Version: 2.4
Name: flux-reload
Version: 0.1.0
Summary: Universal Hot-Reload Manager
Author-email: Ashutosh Singh <ashutoshsingh@gmail.com>
License: MIT
Keywords: hot-reload,watch,cli,flux
Requires-Python: >=3.11
Requires-Dist: click>=8.1.8
Requires-Dist: PyYAML>=6.0.2
Requires-Dist: pytest>=8.3.5
Requires-Dist: pytest-asyncio>=0.26.0
Requires-Dist: watchdog>=6.0.0
